mlx_contentvec/__init__.py
mlx_contentvec/contentvec.py
mlx_contentvec/conv_feature_extraction.py
mlx_contentvec/transformer_encoder.py
mlx_contentvec/modules/__init__.py
mlx_contentvec/modules/cond_layer_norm.py
mlx_contentvec/modules/group_norm.py
mlx_contentvec/modules/multihead_attention.py
mlx_contentvec/modules/weight_norm.py
mlx_contentvec/wav2vec/wav2vec.py
mlx_contentvec-0.1.1.dist-info/METADATA
mlx_contentvec-0.1.1.dist-info/WHEEL
mlx_contentvec-0.1.1.dist-info/top_level.txt
mlx_contentvec-0.1.1.dist-info/RECORD
