Metadata-Version: 2.4
Name: mlx-contentvec
Version: 0.1.1
Summary: MLX implementation of ContentVec/HuBERT for Apple Silicon
License: MIT
Project-URL: Homepage, https://github.com/lexandstuff/mlx-contentvec
Project-URL: Repository, https://github.com/lexandstuff/mlx-contentvec
Project-URL: Bug Tracker, https://github.com/lexandstuff/mlx-contentvec/issues
Project-URL: Model Weights, https://huggingface.co/lexandstuff/mlx-contentvec
Keywords: mlx,contentvec,hubert,audio,speech,voice-conversion,rvc,apple-silicon
Classifier: Development Status :: 4 - Beta
Classifier: Intended Audience :: Developers
Classifier: Intended Audience :: Science/Research
Classifier: License :: OSI Approved :: MIT License
Classifier: Operating System :: MacOS :: MacOS X
Classifier: Programming Language :: Python :: 3
Classifier: Programming Language :: Python :: 3.11
Classifier: Programming Language :: Python :: 3.12
Classifier: Topic :: Scientific/Engineering :: Artificial Intelligence
Classifier: Topic :: Multimedia :: Sound/Audio :: Speech
Requires-Python: >=3.11
Requires-Dist: huggingface-hub>=1.3.2
Requires-Dist: librosa>=0.11.0
Requires-Dist: mlx>=0.29.3
Requires-Dist: npy-append-array>=0.9.19
Requires-Dist: safetensors>=0.7.0
Requires-Dist: soundfile>=0.13.1
Provides-Extra: dev
Requires-Dist: pytest>=8.0.0; extra == "dev"
Requires-Dist: torch>=2.0.0; extra == "dev"
Requires-Dist: numpy>=1.24.0; extra == "dev"
Requires-Dist: ruff>=0.8.0; extra == "dev"
Requires-Dist: omegaconf>=2.0.0; extra == "dev"
